nupic.bindings-1.0.6-py2.7-nspkg.pth
nupic/dummy.pyd
nupic/bindings/__init__.py
nupic/bindings/_algorithms.pyd
nupic/bindings/_engine_internal.pyd
nupic/bindings/_math.pyd
nupic/bindings/algorithms.py
nupic/bindings/check.py
nupic/bindings/engine_internal.py
nupic/bindings/math.py
nupic/bindings/regions/PyRegion.py
nupic/bindings/regions/TestNode.py
nupic/bindings/regions/__init__.py
nupic/bindings/tools/SerializationTestPyRegionProto.capnp
nupic/bindings/tools/__init__.py
nupic/bindings/tools/cyclical_serialization_perf.py
nupic/bindings/tools/random_serialization_perf.py
nupic/bindings/tools/serialization_test_py_region.py
nupic/proto/ArrayProto.capnp
nupic/proto/BitHistory.capnp
nupic/proto/Cell.capnp
nupic/proto/Cells4.capnp
nupic/proto/ClaClassifier.capnp
nupic/proto/ConnectionsProto.capnp
nupic/proto/LinkProto.capnp
nupic/proto/Map.capnp
nupic/proto/NetworkProto.capnp
nupic/proto/PyRegionProto.capnp
nupic/proto/RandomProto.capnp
nupic/proto/RegionProto.capnp
nupic/proto/SdrClassifier.capnp
nupic/proto/Segment.capnp
nupic/proto/SegmentUpdate.capnp
nupic/proto/SparseBinaryMatrixProto.capnp
nupic/proto/SparseMatrixProto.capnp
nupic/proto/SpatialPoolerProto.capnp
nupic/proto/SvmProto.capnp
nupic/proto/TemporalMemoryProto.capnp
nupic/proto/TemporalMemoryV1.capnp
nupic/proto/TestNodeProto.capnp
nupic/proto/VectorFileSensorProto.capnp
nupic/proto/__init__.py
nupic.bindings-1.0.6.dist-info/DESCRIPTION.rst
nupic.bindings-1.0.6.dist-info/METADATA
nupic.bindings-1.0.6.dist-info/RECORD
nupic.bindings-1.0.6.dist-info/WHEEL
nupic.bindings-1.0.6.dist-info/entry_points.txt
nupic.bindings-1.0.6.dist-info/metadata.json
nupic.bindings-1.0.6.dist-info/namespace_packages.txt
nupic.bindings-1.0.6.dist-info/top_level.txt
