Metadata-Version: 2.0
Name: nupic.bindings
Version: 1.0.6
Summary: Numenta Platform for Intelligent Computing - bindings
Home-page: https://github.com/numenta/nupic.core
Author: Numenta
Author-email: help@numenta.org
License: UNKNOWN
Platform: UNKNOWN
Classifier: Programming Language :: Python
Classifier: Programming Language :: Python :: 2
Classifier: License :: OSI Approved :: GNU Affero General Public License v3 or later (AGPLv3+)
Classifier: Operating System :: MacOS :: MacOS X
Classifier: Operating System :: POSIX :: Linux
Classifier: Operating System :: Microsoft :: Windows
Classifier: Development Status :: 5 - Production/Stable
Classifier: Environment :: Console
Classifier: Intended Audience :: Science/Research
Classifier: Topic :: Scientific/Engineering :: Artificial Intelligence
Provides-Extra: capnp
Requires-Dist: numpy (==1.12.1)
Requires-Dist: pytest (==3.0.7)
Requires-Dist: pytest-cov (==2.5.0)
Requires-Dist: pytest-xdist (==1.16.0)
Provides-Extra: capnp
Requires-Dist: pycapnp (==0.6.3); extra == 'capnp'
